{
    "type": "object",
    "properties": {
        "idHash": {
            "$ref": "../meta/secure-hash-config.json"
        },
        "idLength": {
            "description": "Number of bytes for generated IDs.",
            "type": "integer",
            "minimum": 8
        },
        "lifetime": {
            "$ref": "time-offset.json"
        },
        "storagePrefix": {
            "$ref": "storage-prefix.json"
        }
    },
    "required": [
        "idHash",
        "idLength",
        "lifetime",
        "storagePrefix"
    ]
}
